skos_api/__init__.py
skos_api-1.1.0.dist-info/METADATA
skos_api-1.1.0.dist-info/WHEEL
skos_api-1.1.0.dist-info/RECORD
